{
    "data": [
        {
            "brand": "Loreal Paris Men",
            "name": "Loreal Paris Men",
            "value": 40140
        },
        {
            "brand": "Pantene",
            "name": "Pantene",
            "value": 27836
        },
        {
            "brand": "Rejoice",
            "name": "Rejoice",
            "value": 9855
        },
        {
            "brand": "VS",
            "name": "VS",
            "value": 6111
        },
        {
            "brand": "HNS",
            "name": "HNS",
            "value": 5097
        },
        {
            "brand": "Loreal Paris",
            "name": "Loreal Paris",
            "value": 4059
        },
        {
            "brand": "Seeyoung",
            "name": "Seeyoung",
            "value": 3097
        },
        {
            "brand": "Lux",
            "name": "Lux",
            "value": 2332
        },
        {
            "brand": "Dove",
            "name": "Dove",
            "value": 1303
        },
        {
            "brand": "Clear",
            "name": "Clear",
            "value": 1300
        }
    ]
}
